pdfino/__init__.py
pdfino/django.py
pdfino/main.py
pdfino/py.typed
pdfino/styles.py
pdfino/type_definitions.py
pdfino/utils.py
pdfino-0.1.0.dist-info/LICENSE
pdfino-0.1.0.dist-info/METADATA
pdfino-0.1.0.dist-info/WHEEL
pdfino-0.1.0.dist-info/RECORD
