Metadata-Version: 2.1
Name: pdfino
Version: 0.1.0
Summary: A thin wrapper around ReportLab designed to simplify PDF document creation.
Home-page: https://github.com/eillarra/pdfino
License: MIT
Keywords: pdf,reportlab
Author: Eneko Illarramendi
Author-email: eneko@illarra.com
Requires-Python: >=3.8,<4
Classifier: Development Status :: 4 - Beta
Classifier: Intended Audience :: Developers
Classifier: License :: OSI Approved :: MIT License
Classifier: Operating System :: OS Independent
Classifier: Programming Language :: Python
Classifier: Programming Language :: Python :: 3
Classifier: Programming Language :: Python :: 3.8
Classifier: Programming Language :: Python :: 3.9
Classifier: Programming Language :: Python :: 3.10
Classifier: Programming Language :: Python :: 3.11
Classifier: Programming Language :: Python :: 3.12
Classifier: Topic :: Software Development :: Libraries :: Python Modules
Classifier: Typing :: Typed
Provides-Extra: markdown
Requires-Dist: pillow (>=10.0.1)
Requires-Dist: reportlab (>=4.0,<5.0)
Requires-Dist: svglib
Project-URL: Documentation, https://pdfino.readthedocs.io/
Project-URL: Repository, https://github.com/eillarra/pdfino
